pytags/__init__.py
pytags/cmdline.py
pytags/config.py
pytags/mgr.py
pytags/static.py
pytags/tagger.py
pytags/utils/__init__.py
pytags/utils/boot.py
pytags-0.0.12.dist-info/LICENSE
pytags-0.0.12.dist-info/METADATA
pytags-0.0.12.dist-info/WHEEL
pytags-0.0.12.dist-info/entry_points.txt
pytags-0.0.12.dist-info/top_level.txt
pytags-0.0.12.dist-info/RECORD
