Metadata-Version: 2.1
Name: pytags
Version: 0.0.12
Summary: module to help you tag interesting places in your code
Home-page: https://veltzer.github.io/pytags
Download-URL: https://github.com/veltzer/pytags
Author: Mark Veltzer
Author-email: mark.veltzer@gmail.com
Maintainer: Mark Veltzer
Maintainer-email: mark.veltzer@gmail.com
License: MIT
Keywords: pytags,tag,code,command,line
Platform: python3
Classifier: Development Status :: 4 - Beta
Classifier: Environment :: Console
Classifier: Operating System :: OS Independent
Classifier: Programming Language :: Python
Classifier: Programming Language :: Python :: 3
Classifier: Programming Language :: Python :: 3 :: Only
Classifier: Programming Language :: Python :: 3.11
Classifier: Topic :: Utilities
Classifier: License :: OSI Approved :: MIT License
License-File: LICENSE
Requires-Dist: pytconf
Requires-Dist: pylogconf
Requires-Dist: mysql.connector
